__init__.py
__main__.py
message.py
tarric_pypi_test-1.0.0.dist-info/METADATA
tarric_pypi_test-1.0.0.dist-info/WHEEL
tarric_pypi_test-1.0.0.dist-info/top_level.txt
tarric_pypi_test-1.0.0.dist-info/RECORD
