Metadata-Version: 2.1
Name: tarric-pypi-test
Version: 1.0.0
Summary: Test package for tarric
Author-email: Tarric Sookdeo <tarricsookdeo@outlook.com>
Project-URL: Homepage, https://github.com/tarricsookdeo/tarric-pypi-test
Keywords: tarric,pypi,test
Classifier: License :: OSI Approved :: MIT License
Classifier: Programming Language :: Python
Classifier: Programming Language :: Python :: 3
Requires-Python: >=3.10
Provides-Extra: dev
Requires-Dist: autopep8 ; extra == 'dev'
